lizhiphysicsl/Units.py
lizhiphysicsl/__init__.py
lizhiphysicsl/density.py
lizhiphysicsl/phymath.py
lizhiphysicsl/pressure.py
lizhiphysicsl/velocity.py
lizhiphysicsl/middle_school/__init__.py
lizhiphysicsl/middle_school/density.py
lizhiphysicsl/middle_school/phymath.py
lizhiphysicsl/middle_school/pressure.py
lizhiphysicsl/middle_school/veloity.py
lizhiphysics-0.1.1.dist-info/METADATA
lizhiphysics-0.1.1.dist-info/WHEEL
lizhiphysics-0.1.1.dist-info/top_level.txt
lizhiphysics-0.1.1.dist-info/RECORD
