Metadata-Version: 2.1
Name: lizhiphysics
Version: 0.1.1
Summary: A light weight command physics that supports Windows, MacOS, and Linux
Author: clever chen
Author-email: 
Keywords: python,physics,荔枝,windows,mac,linux,phy,math,v
Classifier: Development Status :: 1 - Planning
Classifier: Intended Audience :: Developers
Classifier: Programming Language :: Python :: 3
Classifier: Operating System :: Unix
Classifier: Operating System :: MacOS :: MacOS X
Classifier: Operating System :: Microsoft :: Windows
Requires-Dist: numpy
Requires-Dist: sympy
Requires-Dist: getch ; platform_system == "MacOS"
Requires-Dist: getch ; platform_system == "Unix"
